traficsignal.v
module traficsignal(RYG1,RYG2,RYG3,RYG4,T,rst,clk);
input rst,clk;
input [3:0] T;
output reg [2:0] RYG1,RYG2,RYG3,RYG4;
always @ (posedge clk) begin
        if (rst) begin
                RYG1 <= 3'b010;
                RYG2 <= 3'b010;
                RYG3 <= 3'b010;
                RYG4 <= 3'b010;
        end else begin
                if (T == 4'b0000) begin
                        RYG1 <= 3'b010;
                        RYG2 <= 3'b010;
                        RYG3 <= 3'b010;
                        RYG4 <= 3'b010; 
                end else begin
                        if (T[0] == 1'b1) begin
                                RYG1 <= 3'b001;
                                RYG2 <= 3'b100;
                                RYG3 <= 3'b100;
                                RYG4 <= 3'b100; 
                        end else if (T[1] == 1'b1) begin
                                RYG1 <= 3'b100;
                                RYG2 <= 3'b001;
                                RYG3 <= 3'b100;
                                RYG4 <= 3'b100; 
                        end else if (T[2] == 1'b1) begin
                                RYG1 <= 3'b100;
                                RYG2 <= 3'b100;
                                RYG3 <= 3'b001;
                                RYG4 <= 3'b100; 
                        end else if (T[3] == 1'b1) begin
                                RYG1 <= 3'b100;
                                RYG2 <= 3'b100;
                                RYG3 <= 3'b100;
                                RYG4 <= 3'b001; 
                        end else begin
                                RYG1 <= RYG1;
                                RYG2 <= RYG2;
                                RYG3 <= RYG3;
                                RYG4 <= RYG4; 
                        end
                end         
        end     
end
endmodule

traficsignal_tb.v
`timescale 1s / 1s
module traficsignal_tb;
reg [3:0] T;
reg rst,clk;
wire [2:0] RYG1,RYG2,RYG3,RYG4;
traficsignal A1 (RYG1,RYG2,RYG3,RYG4,T,rst,clk);
initial begin
        clk = 1'b0;
        rst = 1'b0;
end
always #5 clk = ~clk;
initial begin
        $dumpfile("dump.vcd");
        $dumpvars(0,traficsignal_tb);
        $monitor("at time %t : clk = %b | rst = %b | T = %b | RYG1 = %b | RYG2 = %b | RYG3 = %b | RYG4 = %b",$time,clk,rst,T,RYG1,RYG2,RYG3,RYG4);
                rst = 1'b1 ; #10;
                rst = 1'b0 ; T = 4'b1 ; #10;
                T = 4'b0 ; #10;
                T = 4'b0010 ; #10;
                T = 4'b0100 ; #10;
                T = 4'b1000 ; #10;
        $finish;
end
endmodule

dump.vcd
$date
	Thu Jul 16 14:30:03 2026
$end
$version
	Icarus Verilog
$end
$timescale
	1s
$end
$scope module traficsignal_tb $end
$var wire 3 ! RYG4 [2:0] $end
$var wire 3 " RYG3 [2:0] $end
$var wire 3 # RYG2 [2:0] $end
$var wire 3 $ RYG1 [2:0] $end
$var reg 4 % T [3:0] $end
$var reg 1 & clk $end
$var reg 1 ' rst $end
$scope module A1 $end
$var wire 4 ( T [3:0] $end
$var wire 1 & clk $end
$var wire 1 ' rst $end
$var reg 3 ) RYG1 [2:0] $end
$var reg 3 * RYG2 [2:0] $end
$var reg 3 + RYG3 [2:0] $end
$var reg 3 , RYG4 [2:0] $end
$upscope $end
$upscope $end
$enddefinitions $end
$comment Show the parameter values. $end
$dumpall
$end
#0
$dumpvars
bx ,
bx +
bx *
bx )
bx (
1'
0&
bx %
bx $
bx #
bx "
bx !
$end
#5
b10 !
b10 ,
b10 "
b10 +
b10 #
b10 *
b10 $
b10 )
1&
#10
0&
b1 %
b1 (
0'
#15
b100 !
b100 ,
b100 "
b100 +
b100 #
b100 *
b1 $
b1 )
1&
#20
0&
b0 %
b0 (
#25
b10 !
b10 ,
b10 "
b10 +
b10 #
b10 *
b10 $
b10 )
1&
#30
0&
b10 %
b10 (
#35
b100 !
b100 ,
b100 "
b100 +
b1 #
b1 *
b100 $
b100 )
1&
#40
0&
b100 %
b100 (
#45
b1 "
b1 +
b100 #
b100 *
1&
#50
0&
b1000 %
b1000 (
#55
b1 !
b1 ,
b100 "
b100 +
1&
